snowcli/__about__.py
snowcli/__init__.py
snowcli/config.py
snowcli/snow_connector.py
snowcli/snowsql_config.py
snowcli/utils.py
snowcli/cli/__init__.py
snowcli/cli/connection.py
snowcli/cli/render.py
snowcli/cli/snowpark_shared.py
snowcli/cli/sql.py
snowcli/cli/stage.py
snowcli/cli/streamlit.py
snowcli/cli/warehouse.py
snowcli/cli/common/__init__.py
snowcli/cli/common/flags.py
snowcli/cli/snowpark/__init__.py
snowcli/cli/snowpark/function.py
snowcli/cli/snowpark/package.py
snowcli/cli/snowpark/procedure.py
snowcli/cli/snowpark/procedure_coverage/__init__.py
snowcli/cli/snowpark/procedure_coverage/clear.py
snowcli/cli/snowpark/procedure_coverage/report.py
snowcli/output/__init__.py
snowcli/output/formats.py
snowcli/output/printing.py
snowcli/python_templates/environment.yml.jinja
snowcli/python_templates/snowpark_coverage.py.jinja
snowcli/python_templates/streamlit_app_launcher.py.jinja
snowcli/sql/call_procedure.sql
snowcli/sql/create_function.sql
snowcli/sql/create_procedure.sql
snowcli/sql/create_stage.sql
snowcli/sql/create_streamlit.sql
snowcli/sql/describe_function.sql
snowcli/sql/describe_procedure.sql
snowcli/sql/describe_streamlit.sql
snowcli/sql/drop_function.sql
snowcli/sql/drop_procedure.sql
snowcli/sql/drop_stage.sql
snowcli/sql/drop_streamlit.sql
snowcli/sql/execute_function.sql
snowcli/sql/get_stage.sql
snowcli/sql/get_streamlit_url.sql
snowcli/sql/list_functions.sql
snowcli/sql/list_procedures.sql
snowcli/sql/list_stage.sql
snowcli/sql/list_stages.sql
snowcli/sql/list_streamlits.sql
snowcli/sql/put_stage.sql
snowcli/sql/remove_from_stage.sql
snowcli/sql/set_procedure_comment.sql
snowcli/sql/share_streamlit.sql
snowcli/sql/show_warehouses.sql
templates/__init__.py
templates/default_function/.gitignore
templates/default_function/app.py
templates/default_function/app.toml
templates/default_function/requirements.txt
templates/default_procedure/.gitignore
templates/default_procedure/app.py
templates/default_procedure/app.toml
omnata_snowcli_fork-0.3.1.dist-info/METADATA
omnata_snowcli_fork-0.3.1.dist-info/WHEEL
omnata_snowcli_fork-0.3.1.dist-info/entry_points.txt
omnata_snowcli_fork-0.3.1.dist-info/licenses/LICENSE
omnata_snowcli_fork-0.3.1.dist-info/RECORD
