Metadata-Version: 2.1
Name: omnata-snowcli-fork
Version: 0.3.1
Summary: Snowflake CLI
Project-URL: Source code, https://github.com/Snowflake-Labs/snowcli
Project-URL: Bug Tracker, https://github.com/Snowflake-Labs/snowcli/issues
License-Expression: Apache-2.0
License-File: LICENSE
Classifier: Development Status :: 3 - Alpha
Classifier: Environment :: Console
Classifier: Intended Audience :: Developers
Classifier: Intended Audience :: Information Technology
Classifier: Intended Audience :: System Administrators
Classifier: License :: OSI Approved :: Apache Software License
Classifier: Programming Language :: Python :: 3 :: Only
Classifier: Programming Language :: SQL
Classifier: Topic :: Database
Requires-Python: >=3.8
Requires-Dist: coverage==7.2.6
Requires-Dist: jinja2==3.1.2
Requires-Dist: requests==2.28.1
Requires-Dist: requirements-parser==0.5.0
Requires-Dist: rich==13.4.1
Requires-Dist: snowflake-connector-python==3.0.3
Requires-Dist: toml==0.10.2
Requires-Dist: typer==0.9.0
Provides-Extra: dev
Requires-Dist: pre-commit==3.3.2; extra == 'dev'
Requires-Dist: pytest==7.2.0; extra == 'dev'
Requires-Dist: syrupy==4.0.2; extra == 'dev'
Requires-Dist: tox==4.5.2; extra == 'dev'
